{"Torment":[{"score":"39171519","level":"87","link":"https://www.youtube.com/watch?v=yKdo7p1rF6Y&list=PL_KvBMo1VNtEjgrdTpil15qsu_UC8lGHA&index=5","teams":[["10045","10032","10046","10033","20027","26008"],[["10036"],"10035","10064","10053","20008","20020"]],"uuid":"3004a9a1-ff66-416e-b1fe-b29189090301","author":"NeKuRo"},{"score":"38490078","level":"87","link":"https://www.youtube.com/watch?v=vU0iGgefVEs&list=PL_KvBMo1VNtEjgrdTpil15qsu_UC8lGHA&index=13&t=327s","teams":[["10059","10053","10032","10042","20022","20020"],["10036","10063","16002","13009","20027","20019"],["10033","10061",["10053"],"16012","20025","26001"],["10046","10064","10045","16011","20008","26008"]],"uuid":"53757904-d5a0-4ab8-80e0-d029d002a76c","author":"NeKuRo"},{"score":"39280317","level":"87","link":"https://www.youtube.com/watch?v=nxBVKYwsung&list=PL_KvBMo1VNtEjgrdTpil15qsu_UC8lGHA&index=2","teams":[["10033","10045","10032","10046","26008","20027"],["10035",["10036"],"10064","10053","20008","20020"]],"uuid":"7e74ff94-2ebb-4ad9-95be-cd7753fd25e6","author":"NeKuRo"},{"score":"39269597","level":"87","link":"https://www.youtube.com/watch?v=l13KXaVxdMU&list=PL_KvBMo1VNtEjgrdTpil15qsu_UC8lGHA&index=4&t=7s","teams":[["10033","10045","10046","10032","20027","26008"],["10035",["10036"],"10064","10053","20008","20020"]],"uuid":"16c7973f-6104-469d-9a22-2329f1a74c6f","author":"NeKuRo"},{"score":"38649197","level":"87","link":"https://www.youtube.com/watch?v=YlSIQWNEMlA&list=PL_KvBMo1VNtEjgrdTpil15qsu_UC8lGHA&index=67","teams":[["10059","10053","10032","10029","20022","20020"],["10033","10061",["10053"],"10024","20005","26001"],["10046","10064","10045","16011","20008","26008"]],"uuid":"33f44ede-df6f-41e9-9c6c-d0fb2f9d3826","author":"NeKuRo"},{"score":"38697599","level":"87","link":"https://www.youtube.com/watch?v=L0N3xU9E9RY&list=PL_KvBMo1VNtEjgrdTpil15qsu_UC8lGHA&index=12&t=13s","teams":[["10032","10053","10059","10021","20020","20022"],["10002","10066","13009","10011","20016","20000"],["10064","10033",["10053"],"10046","26001","20027"],["16011","10045","16005","10052","20008","26008"]],"uuid":"f72e5156-21c5-4bd0-9cea-df41fe65f6c3","author":"NeKuRo"},{"score":"38295358","level":"87","link":"https://www.youtube.com/watch?v=nKdNFAKfNR8&list=PL_KvBMo1VNtEjgrdTpil15qsu_UC8lGHA&index=14&t=1s","teams":[["10035","10053","10036","10032","20008","20020"],["10051","10064",["10053"],"10046","26001","20005"],["10045","16011","16005","10050","20027","26008"],["13009","10059","16002","10011","20022","23002"]],"uuid":"544a55c0-12ef-4503-8c02-5302f928575e","author":"NeKuRo"},{"score":"39220238","level":"87","link":"https://www.youtube.com/watch?v=dOWv1Iu9twY&list=PL_KvBMo1VNtEjgrdTpil15qsu_UC8lGHA&index=3&t=6s","teams":[["10033","10045","10032","10046","26008","20025"],[["10053"],"10064","10036","10035","20008","20020"]],"uuid":"9859f7ee-e3f8-4ef3-995d-cf0b38e38f5f","author":"NeKuRo"},{"score":"39319997","level":"87","link":"https://www.youtube.com/watch?v=9X_sVbj8X9E&list=PL_KvBMo1VNtEjgrdTpil15qsu_UC8lGHA&index=9&t=3s","teams":[["10032","10061","10045","10033","26008","20027"],["10064","10036","10053","10035","20020","20008"]],"uuid":"982ce9f0-703d-4227-8f64-affdb109fb47","author":"NeKuRo"},{"score":"39219917","level":"87","link":"https://www.youtube.com/watch?v=hAWH6YDi89Y&list=PL_KvBMo1VNtEjgrdTpil15qsu_UC8lGHA&index=6&t=2s","teams":[["10033","10045","10032","10046","20027","26008"],["10035",["10036"],"10064","10053","20008","20020"]],"uuid":"3a6323e6-3d96-4945-ae01-f91363c3b7a4","author":"NeKuRo"},{"score":"38126319","level":"85","link":"https://www.youtube.com/watch?v=yRwQyLZAOfs&t=5s","teams":[["10017","10021","10053","10032","20020","20022"],["10033","10014",["10053"],"10064","20005","26001"],["10002","16011","10045","16005","20008","26008"],["10036","16002","13009","10011","23004","20016"],["10059","10029","13010","10012","20001","20000"]],"uuid":"83cada81-dc7a-469f-984a-2f602607e765","author":"ooferdoggo"},{"score":"39237277","level":"87","link":"https://www.youtube.com/watch?v=Z2qXXiL3cJk&list=PL_KvBMo1VNtEjgrdTpil15qsu_UC8lGHA&index=8&t=27s","teams":[["10032","10061","10045","10033","26008","20027"],["10064","10036","10035","10053","20008","20020"]],"uuid":"13fcb6d4-aa5a-456d-9f16-73e63c446725","author":"NeKuRo"},{"score":"39230237","level":"87","link":"https://www.youtube.com/watch?v=XBkrYzjksgs&list=PL_KvBMo1VNtEjgrdTpil15qsu_UC8lGHA&index=7&t=1s","teams":[["10033","10045","10032","10046","26008","20027"],["10035",["10036"],"10064","10053","20008","20020"]],"uuid":"8716b60b-6a07-42e0-b5b5-a676f12697af","author":"NeKuRo"}]}